soroush_python_sdk/__init__.py
soroush_python_sdk/soroush_python_sdk.py
soroush_python_sdk-0.2.4.dist-info/AUTHORS.rst
soroush_python_sdk-0.2.4.dist-info/LICENSE
soroush_python_sdk-0.2.4.dist-info/METADATA
soroush_python_sdk-0.2.4.dist-info/WHEEL
soroush_python_sdk-0.2.4.dist-info/top_level.txt
soroush_python_sdk-0.2.4.dist-info/RECORD
