Metadata-Version: 2.1
Name: soroush-python-sdk
Version: 0.2.4
Summary: api to access soroush social network sdk
Home-page: https://github.com/alinik/soroush_python_sdk
Author: Ali Nikneshan
Author-email: ali@nikneshan.com
License: MIT license
Keywords: soroush_python_sdk
Platform: UNKNOWN
Classifier: Development Status :: 2 - Pre-Alpha
Classifier: Intended Audience :: Developers
Classifier: License :: OSI Approved :: MIT License
Classifier: Natural Language :: English
Classifier: Programming Language :: Python :: 2
Classifier: Programming Language :: Python :: 2.7
Classifier: Programming Language :: Python :: 3
Classifier: Programming Language :: Python :: 3.4
Classifier: Programming Language :: Python :: 3.5
Classifier: Programming Language :: Python :: 3.6
Classifier: Programming Language :: Python :: 3.7
